taleteller/__init__.py
taleteller/main.py
taleteller-0.0.0.1.dist-info/LICENSE
taleteller-0.0.0.1.dist-info/METADATA
taleteller-0.0.0.1.dist-info/WHEEL
taleteller-0.0.0.1.dist-info/entry_points.txt
taleteller-0.0.0.1.dist-info/top_level.txt
taleteller-0.0.0.1.dist-info/RECORD
